revChatGPT/V1.py
revChatGPT/V3.py
revChatGPT/__init__.py
revChatGPT/__main__.py
revChatGPT/recipient.py
revChatGPT/typings.py
revChatGPT/utils.py
revChatGPT/config/enable_internet.json
tesla_revChatGPT-5.5.0.dist-info/METADATA
tesla_revChatGPT-5.5.0.dist-info/WHEEL
tesla_revChatGPT-5.5.0.dist-info/top_level.txt
tesla_revChatGPT-5.5.0.dist-info/RECORD
